LICENCE
MANIFEST.in
README.md
httpcat.py
setup.py
httpcat.egg-info/PKG-INFO
httpcat.egg-info/SOURCES.txt
httpcat.egg-info/dependency_links.txt
httpcat.egg-info/entry_points.txt
httpcat.egg-info/pbr.json
httpcat.egg-info/top_level.txt