Metadata-Version: 1.1
Name: httpcat
Version: 0.0.1
Summary: Create raw HTTP requests on the command line.
Home-page: https://github.com/jkbrzt/httpcat
Author: Jakub Roztocil
Author-email: jakub@roztocil.co
License: BSD
Download-URL: https://github.com/jkbrzt/httpcat
Platform: UNKNOWN
Classifier: Development Status :: 5 - Production/Stable
Classifier: Programming Language :: Python :: 3
Classifier: Environment :: Console
Classifier: Intended Audience :: Developers
Classifier: Intended Audience :: System Administrators
Classifier: License :: OSI Approved :: BSD License
Classifier: Topic :: Internet :: WWW/HTTP
Classifier: Topic :: Software Development
Classifier: Topic :: System :: Networking
Classifier: Topic :: Terminals
Classifier: Topic :: Text Processing
Classifier: Topic :: Utilities
